erogaki_wrapper_shared_python/AbstractErogakiWrapperError.py
erogaki_wrapper_shared_python/ErogakiWrapperConfig.py
erogaki_wrapper_shared_python/ImageProcessor.py
erogaki_wrapper_shared_python-0.7.1.dist-info/LICENSE
erogaki_wrapper_shared_python-0.7.1.dist-info/METADATA
erogaki_wrapper_shared_python-0.7.1.dist-info/WHEEL
erogaki_wrapper_shared_python-0.7.1.dist-info/top_level.txt
erogaki_wrapper_shared_python-0.7.1.dist-info/RECORD
